anomaly/__init__.py
anomaly/adtk.py
data_generators/__init__.py
data_generators/synthetic_sales_data.py
profitops_rca-0.1.0.dist-info/licenses/LICENSE
profitops_rca-0.1.0.dist-info/METADATA
profitops_rca-0.1.0.dist-info/WHEEL
profitops_rca-0.1.0.dist-info/top_level.txt
profitops_rca-0.1.0.dist-info/RECORD
