Metadata-Version: 2.4
Name: profitops-rca
Version: 0.1.0
Summary: ProRCA - Root Cause Analysis Tool
Author-email: Ahmed Dawoud <adawoud@profitops.ai>
License: MIT License
Project-URL: Homepage, https://github.com/profitopsai/ProRCA
Project-URL: Bug Tracker, https://github.com/profitopsai/ProRCA/issues
Project-URL: Documentation, https://prorca.readthedocs.io/en/latest/
Classifier: Programming Language :: Python :: 3
Classifier: License :: OSI Approved :: MIT License
Classifier: Operating System :: OS Independent
Requires-Python: >=3.7
License-File: LICENSE
Requires-Dist: dowhy>=0.8
Requires-Dist: networkx>=2.6
Requires-Dist: graphviz>=0.16
Requires-Dist: adtk>=0.6.2
Requires-Dist: matplotlib>=3.4
Requires-Dist: seaborn>=0.11
Requires-Dist: numpy>=1.20
Requires-Dist: pandas>=1.3
Requires-Dist: IPython>=7.31
Provides-Extra: dev
Requires-Dist: pytest>=6.2; extra == "dev"
Requires-Dist: black>=22.3; extra == "dev"
Requires-Dist: flake8>=4.0; extra == "dev"
Requires-Dist: sphinx>=4.0; extra == "dev"
Requires-Dist: sphinx-rtd-theme>=1.0; extra == "dev"
Requires-Dist: myst-parser>=0.18; extra == "dev"
Dynamic: license-file
